timeserieslogger/__init__.py
timeserieslogger/mqtttimeserieslogger.py
mqtttimeserieslogger_tspspi-0.0.5.dist-info/LICENSE.md
mqtttimeserieslogger_tspspi-0.0.5.dist-info/METADATA
mqtttimeserieslogger_tspspi-0.0.5.dist-info/WHEEL
mqtttimeserieslogger_tspspi-0.0.5.dist-info/entry_points.txt
mqtttimeserieslogger_tspspi-0.0.5.dist-info/top_level.txt
mqtttimeserieslogger_tspspi-0.0.5.dist-info/RECORD
