Metadata-Version: 2.1
Name: mqtttimeserieslogger-tspspi
Version: 0.0.5
Summary: A very simple NPZ file time series logger for MQTT events
Home-page: https://github.com/tspspi/mqtttimeserieslogger
Author: Thomas Spielauer
Author-email: pypipackages01@tspi.at
Classifier: Programming Language :: Python :: 3
Classifier: License :: OSI Approved :: BSD License
Classifier: Operating System :: POSIX :: BSD :: FreeBSD
Requires-Python: >=3.6
License-File: LICENSE.md
Requires-Dist: daemonize>=2.5.0
Requires-Dist: lockfile>=0.12.2
Requires-Dist: numpy>=1.26.0
Requires-Dist: paho-mqtt>=2.1.0
